local_candles/__init__.py
local_candles/data.py
local_candles/models/__init__.py
local_candles/models/interval.py
local_candles/models/time.py
local_candles/sources/__init__.py
local_candles/sources/base.py
local_candles/sources/binance_spot_ohlc.py
local_candles/sources/binance_usdm_futures_ohlc.py
local_candles/sources/csv_file.py
local_candles/sources/gateio_spot_ohlc.py
local_candles/sources/yahoo_finance_ohlc.py
local_candles/utils.py
local_candles-0.2.5.dist-info/METADATA
local_candles-0.2.5.dist-info/WHEEL
local_candles-0.2.5.dist-info/RECORD
