Metadata-Version: 2.1
Name: local-candles
Version: 0.2.5
Summary: Candles (ohlc) loaders and cache
Home-page: https://github.com/nanvel/local-candles
License: MIT
Keywords: quant,trading,crypto,cancles,ohlc,ohlcv,dataframe,pandas
Author: Oleksandr Polieno
Author-email: polyenoom@gmail.com
Requires-Python: >=3.8,<4.0
Classifier: License :: OSI Approved :: MIT License
Classifier: Programming Language :: Python :: 3
Classifier: Programming Language :: Python :: 3.8
Classifier: Programming Language :: Python :: 3.9
Classifier: Programming Language :: Python :: 3.10
Classifier: Programming Language :: Python :: 3.11
Classifier: Programming Language :: Python :: 3.12
Classifier: Programming Language :: Python :: 3.13
Requires-Dist: pandas (>=2.0.2,<3.0.0)
Requires-Dist: requests (>=2.31.0,<3.0.0)
Project-URL: Repository, https://github.com/nanvel/local-candles
